melli_code/__init__.py
melli_code/exceptions.py
melli_code/generator.py
melli_code/validator.py
melli_code-1.0.1.dist-info/licenses/LICENSE
melli_code-1.0.1.dist-info/METADATA
melli_code-1.0.1.dist-info/WHEEL
melli_code-1.0.1.dist-info/top_level.txt
melli_code-1.0.1.dist-info/RECORD
