Metadata-Version: 2.4
Name: melli-code
Version: 1.0.1
Summary: Python library to validate and generate Iranian National Codes (Melli Code).
Author-email: Amirhosein Vedadi <amirhsein.vedadi@gmail.com>
License: MIT License
Project-URL: Homepage, https://github.com/amirhosein-vedadi/Melli_Code
Project-URL: Repository, https://github.com/amirhosein-vedadi/Melli_Code
Keywords: iran,national code,melli code,validation,generation,کد ملی,ایران
Classifier: Development Status :: 5 - Production/Stable
Classifier: Intended Audience :: Developers
Classifier: License :: OSI Approved :: MIT License
Classifier: Operating System :: OS Independent
Classifier: Programming Language :: Python :: 3
Classifier: Programming Language :: Python :: 3.7
Classifier: Programming Language :: Python :: 3.8
Classifier: Programming Language :: Python :: 3.9
Classifier: Programming Language :: Python :: 3.10
Classifier: Programming Language :: Python :: 3.11
Classifier: Programming Language :: Python :: 3.12
Classifier: Topic :: Software Development :: Libraries :: Python Modules
Classifier: Topic :: Utilities
Classifier: Natural Language :: Persian
Requires-Python: >=3.7
License-File: LICENSE
Provides-Extra: dev
Requires-Dist: pytest>=6.0; extra == "dev"
Requires-Dist: build; extra == "dev"
Requires-Dist: twine; extra == "dev"
Dynamic: license-file
